<?xml version="1.0" encoding="UTF-8" ?>
<SerioCommands version="1.0">
	<DisplayForm>
		<Script>
			<![CDATA[<?xml version="1.0" encoding="UTF-8"?>
			<UiScreen infoLevel="Normal">

				<Operations>
					<Op type="Submit"	action="./UIJOB_TEST.xml"></Op>
					<Op type="Back"		action="./UIJOB_TEST.xml"></Op>
				</Operations>

				<IoScreen>
					<IoObject>

						<Title>CPAPI_UISCR_TEMPLATE_CARD</Title>

						<Description>Swipe card</Description>

						<IdScanner id="card">
							<Label>Idscanner test</Label>
							<Message imgsrc="http://10.145.40.87/dtest/uijob/IMAGE.jpg">Card With Image</Message>
						</IdScanner>

					</IoObject>
				</IoScreen>
			</UiScreen>
			]]>
		</Script>
	</DisplayForm>
</SerioCommands>
