<?xml version="1.0" encoding="utf-8"?>
<!--
-->
<SerioCommands version="v009">
   <DisplayForm>
      <Script>
         <![CDATA[
         <UiScreen infoLevel="Normal">
            <Title>title</Title>
            <AutoTransition>10</AutoTransition>            
            <Operations>
               <!-- <Op type="Submit" action="./c2/7.xml"> -->
               <Op type="Submit" />
            </Operations>
            <IoScreen>
               <IoObject>
                  <Title>IoObject Title 31</Title>
                  <Description>IoObject Description  31</Description>
                  <Message imgsrc="http://10.244.4.135/star.jpg">HERE</Message>
               </IoObject> 
            </IoScreen>
         </UiScreen>
         ]]>
   </Script> </DisplayForm>
</SerioCommands>
